Metadata-Version: 2.1
Name: rozipinfo
Version: 1.0.34
Summary: Managing Zip archives with RISC OS filetype information present
Home-page: https://github.com/gerph/python-zipinfo-riscos
Author: Charles Ferguson
Author-email: gerph@gerph.org
License: BSD
Keywords: zip,riscos
Platform: UNKNOWN
Classifier: Development Status :: 4 - Beta
Classifier: Intended Audience :: Developers
Classifier: License :: OSI Approved :: BSD License
Classifier: Programming Language :: Python :: 2.7
Classifier: Programming Language :: Python :: 3
Classifier: Operating System :: OS Independent
Classifier: Operating System :: RISC OS
Requires-Python: >=2.7
